flattentool/ODSReader.py
flattentool/__init__.py
flattentool/cli.py
flattentool/exceptions.py
flattentool/i18n.py
flattentool/input.py
flattentool/json_input.py
flattentool/lib.py
flattentool/output.py
flattentool/schema.py
flattentool/sheet.py
flattentool/sort_xml.py
flattentool/xml_output.py
flattentool/locale/en/LC_MESSAGES/flatten-tool.mo
flattentool/locale/en/LC_MESSAGES/flatten-tool.po
flattentool/locale/es/LC_MESSAGES/flatten-tool.mo
flattentool/locale/es/LC_MESSAGES/flatten-tool.po
flattentool-0.26.0.data/scripts/flatten-tool
flattentool-0.26.0.dist-info/LICENSE
flattentool-0.26.0.dist-info/METADATA
flattentool-0.26.0.dist-info/WHEEL
flattentool-0.26.0.dist-info/top_level.txt
flattentool-0.26.0.dist-info/RECORD
