Metadata-Version: 2.1
Name: flattentool
Version: 0.26.0
Summary: Tools for generating CSV and other flat versions of the structured data
Home-page: https://github.com/OpenDataServices/flatten-tool
Author: Open Data Services
Author-email: code@opendataservices.coop
License: MIT
Platform: UNKNOWN
License-File: LICENSE
Requires-Dist: ijson
Requires-Dist: jsonref
Requires-Dist: lxml
Requires-Dist: odfpy
Requires-Dist: openpyxl (!=3.0.2,>=2.6)
Requires-Dist: pytz
Requires-Dist: schema
Requires-Dist: xmltodict
Requires-Dist: zc.zlibstorage
Requires-Dist: zodb
Requires-Dist: backports-datetime-fromisoformat ; platform_python_implementation != "PyPy"
Provides-Extra: http
Requires-Dist: requests ; extra == 'http'
Provides-Extra: geo
Requires-Dist: geojson ; extra == 'geo'
Requires-Dist: shapely ; extra == 'geo'
